pltools/__init__.py
pltools/__main__.py
pltools/gittools.py
pycommon/README.md
pycommon/__init__.py
pycommon/exe_cmd.py
patchlion-0.0.4.dist-info/METADATA
patchlion-0.0.4.dist-info/WHEEL
patchlion-0.0.4.dist-info/entry_points.txt
patchlion-0.0.4.dist-info/top_level.txt
patchlion-0.0.4.dist-info/RECORD
